pyagentix/__init__.py
pyagentix/agent.py
pyagentix/chatbot.py
pyagentix/config.py
pyagentix/llm.py
pyagentix/metadata.py
pyagentix/utils.py
pyagentix-0.1.5.dist-info/licenses/LICENSE
pyagentix-0.1.5.dist-info/METADATA
pyagentix-0.1.5.dist-info/WHEEL
pyagentix-0.1.5.dist-info/top_level.txt
pyagentix-0.1.5.dist-info/RECORD
